{"actor":"codex-gale-prd","entity":"bd-01KY8P0G38H93RPVEWW37GG3H2","kind":"note","note_kind":"decision","op":"20260723T235253.752416Z-p38552-c0000-rceb8-h6cbfa5","text":"All four recovered tips are duplicate or pre-review versions of work already on main: PCA paths match cef6347, dense SVD is superseded by cef6347, FFM differs from 5102600 only by a missing policy comment, and 68bebbf has the same patch-id as b065c4e. Preserve ancestry with an ours merge; do not overwrite the reviewed main tree.","ts":"2026-07-23T23:52:53.752416Z","v":1}